wfc3tools/__init__.py
wfc3tools/calwf3.py
wfc3tools/embedsub.py
wfc3tools/pstack.py
wfc3tools/pstat.py
wfc3tools/sampinfo.py
wfc3tools/sub2full.py
wfc3tools/util.py
wfc3tools/version.py
wfc3tools/wf32d.py
wfc3tools/wf3ccd.py
wfc3tools/wf3cte.py
wfc3tools/wf3ir.py
wfc3tools/wf3rej.py
wfc3tools-1.6.0.dist-info/licenses/LICENSE.txt
wfc3tools-1.6.0.dist-info/METADATA
wfc3tools-1.6.0.dist-info/WHEEL
wfc3tools-1.6.0.dist-info/top_level.txt
wfc3tools-1.6.0.dist-info/RECORD
