Metadata-Version: 2.4
Name: wfc3tools
Version: 1.6.0
Summary: Python Tools for HST WFC3 Data
Author: STScI
Project-URL: Homepage, http://wfc3tools.readthedocs.io/
Project-URL: Bug Reports, https://github.com/spacetelescope/wfc3tools/issues/
Project-URL: Source, https://github.com/spacetelescope/wfc3tools/
Project-URL: Help, https://hsthelp.stsci.edu
Classifier: Intended Audience :: Science/Research
Classifier: Operating System :: OS Independent
Classifier: Programming Language :: Python
Classifier: Topic :: Scientific/Engineering :: Astronomy
Classifier: Topic :: Software Development :: Libraries :: Python Modules
Requires-Python: >=3.9
License-File: LICENSE.txt
Requires-Dist: astropy>=4.2.0
Requires-Dist: numpy>=1.21.0
Requires-Dist: matplotlib>=3.5.1
Requires-Dist: stsci.tools>=4.0.1
Requires-Dist: scipy>=1.8.0
Provides-Extra: tests
Requires-Dist: pytest; extra == "tests"
Requires-Dist: astroquery; extra == "tests"
Provides-Extra: docs
Requires-Dist: sphinx; extra == "docs"
Requires-Dist: sphinx-automodapi; extra == "docs"
Requires-Dist: sphinx-rtd-theme; extra == "docs"
Dynamic: license-file
